Agent99/Chat99.py
Agent99/__init__.py
Agent99/response_generator.py
Agent99/search_util.py
Agent99/test_response_generator.py
Agent99/tool_manager.py
Agent99-0.0.1.dist-info/LICENSE
Agent99-0.0.1.dist-info/METADATA
Agent99-0.0.1.dist-info/WHEEL
Agent99-0.0.1.dist-info/top_level.txt
Agent99-0.0.1.dist-info/RECORD
